README.md
setup.py
dampr/__init__.py
dampr/base.py
dampr/buf_reader.py
dampr/dampr.py
dampr/dataset.py
dampr/graph.py
dampr/inputs.py
dampr/memory.py
dampr/runner.py
dampr/settings.py
dampr/stagerunner.py
dampr/utils.py
dampr.egg-info/PKG-INFO
dampr.egg-info/SOURCES.txt
dampr.egg-info/dependency_links.txt
dampr.egg-info/top_level.txt
tests/__init__.py
tests/test_dampr.py