Metadata-Version: 1.1
Name: dampr
Version: 0.2.1
Summary: Data Processing implementation in Python
Home-page: https://www.github.com/Refefer/Dampr
Author: Andrew Stanton
Author-email: refefer@gmail.com
License: UNKNOWN
Platform: UNKNOWN
Classifier: Development Status :: 4 - Beta
Classifier: License :: OSI Approved :: Apache Software License
Classifier: Programming Language :: Python :: 2
Classifier: Programming Language :: Python :: 3
Classifier: Operating System :: OS Independent
